forsake/__init__.py
forsake/cli.py
forsake/client.py
forsake/forker.py
forsake/rpc.py
forsake/server.py
forsake-0.1.0.dist-info/METADATA
forsake-0.1.0.dist-info/WHEEL
forsake-0.1.0.dist-info/entry_points.txt
forsake-0.1.0.dist-info/top_level.txt
forsake-0.1.0.dist-info/RECORD
