Metadata-Version: 2.1
Name: forsake
Version: 0.1.0
Summary: TODO
License: GPL 3.0+
Requires-Python: >=3.9
Requires-Dist: click
